scrapy_mosquitera/__init__.py
scrapy_mosquitera/mixin.py
scrapy_mosquitera/matchers/__init__.py
scrapy_mosquitera/matchers/date.py
scrapy_mosquitera-0.1.1.dist-info/top_level.txt
scrapy_mosquitera-0.1.1.dist-info/METADATA
scrapy_mosquitera-0.1.1.dist-info/DESCRIPTION.rst
scrapy_mosquitera-0.1.1.dist-info/metadata.json
scrapy_mosquitera-0.1.1.dist-info/WHEEL
scrapy_mosquitera-0.1.1.dist-info/RECORD
