Metadata-Version: 2.0
Name: scrapy-mosquitera
Version: 0.1.1
Summary: Restrict crawl and scraping scope using matchers.
Home-page: https://github.com/scrapinghub/scrapy-mosquitera
Author: Scrapinghub
Author-email: info@scrapinghub.com
License: BSD
Keywords: mosquitera,scrapy-mosquitera
Platform: UNKNOWN
Classifier: Development Status :: 2 - Pre-Alpha
Classifier: Intended Audience :: Developers
Classifier: License :: OSI Approved :: ISC License (ISCL)
Classifier: Natural Language :: English
Classifier: Programming Language :: Python :: 2
Classifier: Programming Language :: Python :: 2.7
Classifier: Programming Language :: Python :: 3
Classifier: Programming Language :: Python :: 3.3
Classifier: Programming Language :: Python :: 3.4
Classifier: Programming Language :: Python :: 3.5
Requires-Dist: scrapy (>=1.1.0rc3)
Requires-Dist: six
Requires-Dist: PyDispatcher (>=2.0.5)
Requires-Dist: dateparser
